seal_rookery/__init__.py
seal_rookery/search.py
seal_rookery/upload_images.py
seal_rookery/seals/seals.json
seal_rookery/seals/orig/acca.png
seal_rookery/seals/orig/afcca.png
seal_rookery/seals/orig/akb.png
seal_rookery/seals/orig/akd.png
seal_rookery/seals/orig/ala.svg
seal_rookery/seals/orig/almb.png
seal_rookery/seals/orig/almd.png
seal_rookery/seals/orig/alnb.png
seal_rookery/seals/orig/alnd.png
seal_rookery/seals/orig/alsb.png
seal_rookery/seals/orig/alsd.png
seal_rookery/seals/orig/aoc.svg
seal_rookery/seals/orig/arb.png
seal_rookery/seals/orig/ared.png
seal_rookery/seals/orig/ariz.png
seal_rookery/seals/orig/ark.svg
seal_rookery/seals/orig/armfor.png
seal_rookery/seals/orig/arwd.png
seal_rookery/seals/orig/asbca.png
seal_rookery/seals/orig/azd.png
seal_rookery/seals/orig/bap1.png
seal_rookery/seals/orig/bap8.png
seal_rookery/seals/orig/bap9.png
seal_rookery/seals/orig/ca1.svg
seal_rookery/seals/orig/ca10.png
seal_rookery/seals/orig/ca11.png
seal_rookery/seals/orig/ca2.png
seal_rookery/seals/orig/ca3.svg
seal_rookery/seals/orig/ca4.png
seal_rookery/seals/orig/ca5.png
seal_rookery/seals/orig/ca6.png
seal_rookery/seals/orig/ca7.png
seal_rookery/seals/orig/ca8.png
seal_rookery/seals/orig/ca9.svg
seal_rookery/seals/orig/cacb.png
seal_rookery/seals/orig/cacd.png
seal_rookery/seals/orig/cadc.png
seal_rookery/seals/orig/caed.png
seal_rookery/seals/orig/cafc.svg
seal_rookery/seals/orig/cal.png
seal_rookery/seals/orig/canb.png
seal_rookery/seals/orig/cand.svg
seal_rookery/seals/orig/casd.png
seal_rookery/seals/orig/cavc.png
seal_rookery/seals/orig/cbca.png
seal_rookery/seals/orig/cit.png
seal_rookery/seals/orig/cjdpa.svg
seal_rookery/seals/orig/cob.png
seal_rookery/seals/orig/cod.png
seal_rookery/seals/orig/compliance.png
seal_rookery/seals/orig/conn.png
seal_rookery/seals/orig/ctb.png
seal_rookery/seals/orig/ctd.png
seal_rookery/seals/orig/dc.png
seal_rookery/seals/orig/dcb.png
seal_rookery/seals/orig/dcd.png
seal_rookery/seals/orig/deb.png
seal_rookery-2.3.1.dist-info/LICENSE.txt
seal_rookery-2.3.1.dist-info/METADATA
seal_rookery-2.3.1.dist-info/WHEEL
seal_rookery-2.3.1.dist-info/top_level.txt
seal_rookery-2.3.1.dist-info/RECORD
