Metadata-Version: 2.2
Name: seal_rookery
Version: 2.3.1
Summary: A collection of court seals that can be used in any project.
Home-page: https://github.com/freelawproject/seal-rookery
Download-URL: https://github.com/freelawproject/seal-rookery/archive/2.3.1.tar.gz
Author: Free Law Project
Author-email: info@free.law
Maintainer: Free Law Project
Maintainer-email: info@free.law
Keywords: legal,seals
Classifier: Development Status :: 5 - Production/Stable
Classifier: Intended Audience :: Developers
Classifier: Natural Language :: English
Classifier: License :: OSI Approved :: BSD License
Classifier: Operating System :: OS Independent
Classifier: Programming Language :: Python
Classifier: Programming Language :: Python :: 3
Classifier: Programming Language :: Python :: 3.9
Classifier: Programming Language :: Python :: 3.10
Classifier: Programming Language :: Python :: 3.11
Classifier: Programming Language :: Python :: 3.12
Classifier: Programming Language :: Python :: Implementation :: CPython
Classifier: Programming Language :: Python :: Implementation :: PyPy
Classifier: Topic :: Software Development :: Libraries :: Python Modules
License-File: LICENSE.txt
Dynamic: author
Dynamic: author-email
Dynamic: classifier
Dynamic: description
Dynamic: description-content-type
Dynamic: download-url
Dynamic: home-page
Dynamic: keywords
Dynamic: maintainer
Dynamic: maintainer-email
Dynamic: summary
